{"cameraMode":{"drawMode":0,"name":"Shaded","section":"Shading Mode"},"sceneLighting":true,"audioPlay":false,"sceneViewState":{"m_AlwaysRefresh":false,"showFog":false,"showSkybox":false,"showFlares":false,"showImageEffects":false,"showParticleSystems":false,"showVisualEffectGraphs":true,"m_FxEnabled":true},"in2DMode":false,"pivot":{"x":-0.6515997052192688,"y":2.232267141342163,"z":-8.636316299438477},"rotation":{"x":-0.14605845510959626,"y":0.5595700740814209,"z":-0.10095741599798203,"w":-0.8095448017120361},"size":5.691976547241211,"orthographic":false}